README.rst
setup.py
normalizeData/normalizeData.py
normalizeData.egg-info/PKG-INFO
normalizeData.egg-info/SOURCES.txt
normalizeData.egg-info/dependency_links.txt
normalizeData.egg-info/not-zip-safe
normalizeData.egg-info/top_level.txt