Metadata-Version: 1.0
Name: normalizeData
Version: 1.0.2
Summary: UNKNOWN
Home-page: https://github.com/sudhir8184/normalizeData
Author: hebbalkarsudhir
Author-email: hebbalkarsudhir@gmail.com
License: AGPL 3.0
Keywords: normalization,data,data cleaning,data normalization
Platform: UNKNOWN
